assignment_codeval/__init__.py
assignment_codeval/ai_benchmark.py
assignment_codeval/canvas_utils.py
assignment_codeval/cli.py
assignment_codeval/commons.py
assignment_codeval/convertMD2Html.py
assignment_codeval/create_assignment.py
assignment_codeval/evaluate.py
assignment_codeval/file_utils.py
assignment_codeval/github_connect.py
assignment_codeval/install_assignment.py
assignment_codeval/recent_comments.py
assignment_codeval/submissions.py
assignment_codeval-0.0.19.dist-info/METADATA
assignment_codeval-0.0.19.dist-info/WHEEL
assignment_codeval-0.0.19.dist-info/entry_points.txt
assignment_codeval-0.0.19.dist-info/top_level.txt
assignment_codeval-0.0.19.dist-info/RECORD
