Metadata-Version: 2.4
Name: assignment-codeval
Version: 0.0.19
Summary: CodEval for evaluating programming assignments
Requires-Python: >=3.12
Requires-Dist: canvasapi==3.3.0
Requires-Dist: click==8.2.1
Requires-Dist: configparser==5.2.0
Requires-Dist: pytz==2021.3
Requires-Dist: requests>=2.28.0
Requires-Dist: pymongo==4.3.3
Requires-Dist: markdown==3.4.1
Requires-Dist: mdx-better-lists>=1.0.0
Requires-Dist: anthropic>=0.39.0
Requires-Dist: openai>=1.0.0
Requires-Dist: google-generativeai>=0.8.0
Provides-Extra: test
Requires-Dist: pytest>=7.0; extra == "test"
